razbi_utils/__init__.py
razbi_utils/core/__init__.py
razbi_utils/core/modules/__init__.py
razbi_utils/core/modules/script_tools.py
razbiutils-0.1.1.dist-info/licenses/LICENSE
razbiutils-0.1.1.dist-info/METADATA
razbiutils-0.1.1.dist-info/WHEEL
razbiutils-0.1.1.dist-info/top_level.txt
razbiutils-0.1.1.dist-info/RECORD
