Metadata-Version: 2.4
Name: RazbiUtils
Version: 0.1.1
Summary: A bunch of miscellaneous utils for scripts/RPA
Author-email: TheRealRazbi <therealrazbi@users.noreply.github.com>
License: MPL-2.0
Project-URL: Homepage, https://github.com/TheRealRazbi/RazbiUtils
Project-URL: Bug Tracker, https://github.com/TheRealRazbi/RazbiUtils/issues
Classifier: Programming Language :: Python :: 3
Classifier: License :: OSI Approved :: Mozilla Public License 2.0 (MPL 2.0)
Classifier: Operating System :: OS Independent
Requires-Python: >=3.8
License-File: LICENSE
Requires-Dist: pywin32<400,>=306
Dynamic: license-file
